Metadata-Version: 2.4
Name: opteryx-catalog
Version: 0.4.25
Summary: Opteryx Cloud Catalog
Author-email: joocer <justin.joyce@joocer.com>
License:                                  Apache License
Project-URL: Homepage, https://github.com/mabel-dev/opteryx-catalog
Keywords: opteryx,catalog,firestore,gcs
Classifier: Development Status :: 4 - Beta
Classifier: Intended Audience :: Developers
Classifier: License :: OSI Approved :: MIT License
Classifier: Programming Language :: Python :: 3
Classifier: Programming Language :: Python :: 3 :: Only
Classifier: Programming Language :: Python :: 3.11
Classifier: Programming Language :: Python :: 3.12
Classifier: Programming Language :: Python :: 3.13
Classifier: Operating System :: OS Independent
Requires-Python: >=3.9
License-File: LICENSE
Requires-Dist: google-cloud-firestore==2.23.0
Requires-Dist: google-cloud-storage==3.8.0
Requires-Dist: orso==0.0.226
Requires-Dist: opteryx-core
Requires-Dist: pyarrow==23.0.0
Requires-Dist: requests==2.32.5
Provides-Extra: webhooks
Requires-Dist: google-cloud-tasks>=2.16.0; extra == "webhooks"
Dynamic: license-file
